mcp_mysql_connect/__init__.py
mcp_mysql_connect/__main__.py
mcp_mysql_connect/mcp_mysql_connect.py
mcp_mysql_connect-1.0.4.dist-info/METADATA
mcp_mysql_connect-1.0.4.dist-info/WHEEL
mcp_mysql_connect-1.0.4.dist-info/entry_points.txt
mcp_mysql_connect-1.0.4.dist-info/licenses/LICENSE.txt
mcp_mysql_connect-1.0.4.dist-info/RECORD
