Metadata-Version: 2.4
Name: mcp_mysql_connect
Version: 1.0.4
Summary: MCP Server to connect the MySQL database
Author-email: Gopika P J <pjgopika44@gmail.com>
License: MIT
License-File: LICENSE.txt
Classifier: License :: OSI Approved :: MIT License
Classifier: Operating System :: OS Independent
Classifier: Programming Language :: Python :: 3
Requires-Python: >=3.11
Requires-Dist: mcp[cli]>=1.6.0
Requires-Dist: mysql-connector-python>=8.3.0
Requires-Dist: python-dotenv>=1.1.0
